setup.py
candy/__init__.py
candy/cli.py
candy/gradle_parser.py
candy/lextab.py
candy/local_database.json
candy/manifest_parser.py
candy/registry.json
candy.egg-info/PKG-INFO
candy.egg-info/SOURCES.txt
candy.egg-info/dependency_links.txt
candy.egg-info/entry_points.txt
candy.egg-info/requires.txt
candy.egg-info/top_level.txt