Metadata-Version: 1.1
Name: candy
Version: 0.1.0a1
Summary: Package/Library Manager for Android Apps
Home-page: https://github.com/mingyuan-xia/candy
Author: Mingyuan Xia
Author-email: UNKNOWN
License: Apache v2
Keywords: Android package-manager automation
Platform: UNKNOWN
Classifier: Development Status :: 3 - Alpha
Classifier: Intended Audience :: Developers
Classifier: Intended Audience :: Science/Research
Classifier: Topic :: Utilities
Classifier: License :: OSI Approved :: Apache Software License
Classifier: Environment :: Console
Classifier: Operating System :: POSIX :: Linux
Classifier: Operating System :: Unix
Classifier: Programming Language :: Python :: 2
Classifier: Programming Language :: Python :: 2.7
